{"skeleton":{"width":688.15,"height":640.14,"fps":24,"hash":" ","name":"broken_robot3"},"bones":[{"x":0.5196,"y":0.1003,"name":"root"},{"length":50,"x":96.1491,"y":82.1624,"name":"bone_ikTarget","parent":"root"},{"length":209,"x":1.8923,"y":255.7209,"rotation":90.5764,"name":"bone","parent":"root"},{"length":50,"x":-186.396,"y":270.8091,"rotation":-37.9734,"name":"bone_ikTarget2","parent":"root"},{"length":50,"x":-71.1833,"y":67.7801,"name":"bone_ikTarget1","parent":"root"},{"length":50,"x":138.0871,"y":319.5414,"rotation":-59.4156,"name":"bone_ikTarget3","parent":"root"},{"length":131,"x":-514.7696,"y":307.9997,"rotation":90,"name":"bone19","parent":"root"},{"length":128,"x":-522.0696,"y":213.3997,"rotation":-90,"name":"bone20","parent":"root"},{"length":169,"x":-568.0393,"y":32.788,"rotation":90,"name":"bone22","parent":"root"},{"length":116,"x":-556.0196,"y":254.5997,"rotation":-177.6151,"name":"bone21","parent":"root"},{"length":65,"x":632.1096,"y":157.8603,"rotation":89.2092,"scaleX":2,"scaleY":2,"name":"bone23","parent":"root"},{"x":-15.0142,"y":-100.7453,"scaleX":2.2861,"scaleY":2.2861,"name":"bone_ikTarget4","parent":"bone_ikTarget1"},{"x":17.6752,"y":-108.2723,"scaleX":2.3928,"scaleY":2.3928,"name":"bone_ikTarget5","parent":"bone_ikTarget"},{"length":132,"x":168.8124,"y":-166.6778,"rotation":-119.1119,"name":"bone1","parent":"bone"},{"length":91,"x":-22.286,"y":68.056,"rotation":-155.3829,"name":"bone10","parent":"bone"},{"length":105,"x":134.0915,"y":101.7278,"rotation":-143.3929,"name":"bone15","parent":"bone"},{"length":114,"x":-3.0167,"y":-100.1991,"rotation":-144.5252,"name":"bone5","parent":"bone"},{"length":164,"x":108.837,"y":17.3032,"rotation":-97.5323,"name":"bone16","parent":"bone15"},{"length":146,"x":134.793,"y":31.5593,"rotation":-72.816,"name":"bone2","parent":"bone1"},{"length":78,"x":114.8443,"rotation":-71.513,"name":"bone6","parent":"bone5"},{"length":82,"x":106.9036,"y":9.1788,"rotation":-67.7364,"name":"bone11","parent":"bone10"},{"length":94,"x":187.8489,"y":12.5391,"rotation":37.3416,"name":"bone18","parent":"bone16"},{"length":111,"x":153.1061,"y":9.2373,"rotation":34.7786,"name":"bone3","parent":"bone2"},{"length":65,"x":72.6429,"y":-4.1636,"rotation":32.1526,"name":"bone12","parent":"bone11"},{"length":80,"x":77.5272,"y":8.9692,"rotation":41.4813,"name":"bone7","parent":"bone6"},{"length":91,"x":170.7689,"y":-17.2054,"rotation":-44.1498,"name":"bone4","parent":"bone2"},{"length":134,"x":164.0099,"rotation":-37.3364,"name":"bone17","parent":"bone16"},{"length":86,"x":34.3805,"y":-24.5937,"rotation":-49.5408,"name":"bone13","parent":"bone12"},{"length":62,"x":20.0059,"y":-21.9403,"rotation":-63.3407,"name":"bone8","parent":"bone7"},{"length":61,"x":48.2782,"y":24.9961,"rotation":91.5973,"name":"bone14","parent":"bone12"},{"length":58,"x":46.0302,"y":23.2502,"rotation":68.6484,"name":"bone9","parent":"bone7"}],"slots":[{"name":"slice7","bone":"bone12","attachment":"slice7"},{"name":"slice18","bone":"bone16","attachment":"slice18"},{"name":"slice15","bone":"bone18","attachment":"slice15"},{"name":"slice14","bone":"root"},{"name":"slice16","bone":"bone17","attachment":"slice16"},{"name":"slice17","bone":"bone15","attachment":"slice17"},{"name":"slice2","bone":"bone10","attachment":"slice2"},{"name":"slice5","bone":"bone11","attachment":"slice5"},{"name":"slice3","bone":"bone5","attachment":"slice3"},{"name":"slice6","bone":"bone7","attachment":"slice6"},{"name":"slice8","bone":"bone13","attachment":"slice8"},{"name":"slice9","bone":"bone14","attachment":"slice9"},{"name":"slice4","bone":"bone6","attachment":"slice4"},{"name":"slice10","bone":"bone8","attachment":"slice10"},{"name":"slice11","bone":"bone9","attachment":"slice11"},{"name":"slice1","bone":"bone","attachment":"slice1"},{"name":"slice12","bone":"bone1","attachment":"slice12"},{"name":"slice13","bone":"bone2","attachment":"slice13"},{"name":"slice19","bone":"bone4","attachment":"slice19"},{"name":"slice20","bone":"bone3","attachment":"slice20"},{"name":"fx1","bone":"bone19"},{"name":"fx11","bone":"bone20"},{"name":"fx4","bone":"bone21"},{"name":"fx3","bone":"bone22"},{"name":"explode1","bone":"bone23"},{"name":"slice35","bone":"bone22"}],"ik":[{"bendPositive":false,"name":"bone_ik3","target":"bone_ikTarget3","bones":["bone1","bone2"]},{"bendPositive":false,"name":"bone_ik1","target":"bone_ikTarget1","bones":["bone10","bone11"]},{"bendPositive":false,"name":"bone_ik2","target":"bone_ikTarget2","bones":["bone15","bone16"]},{"bendPositive":false,"name":"bone_ik","target":"bone_ikTarget","bones":["bone5","bone6"]},{"bendPositive":false,"name":"bone_ik4","target":"bone_ikTarget4","bones":["bone12"]},{"bendPositive":false,"name":"bone_ik5","target":"bone_ikTarget5","bones":["bone7"]}],"skins":{"default":{"slice19":{"slice19":{"name":"slice19","width":129,"height":132,"x":60.09,"y":14.2,"rotation":-128.42}},"slice9":{"slice9":{"name":"slice9","width":96,"height":47,"x":21.38,"y":-0.78,"rotation":10.28}},"slice16":{"slice16":{"name":"slice16","width":205,"height":97,"x":73.41,"y":3.66,"rotation":-172.13}},"slice35":{"slice35":{"name":"slice35","width":494,"height":533,"x":175.89,"y":-118.04,"rotation":-90}},"fx4":{"fx4":{"name":"fx4","width":232,"height":93,"x":28.92,"y":-3.58,"rotation":177.62}},"slice1":{"slice1":{"name":"slice1","width":433,"height":418,"x":170.38,"y":-2.38,"rotation":-90.49}},"slice3":{"slice3":{"name":"slice3","width":151,"height":187,"x":49.43,"y":-7.78,"rotation":54.03}},"slice18":{"slice18":{"name":"slice18","width":274,"height":133,"x":110.29,"y":1.52,"rotation":179.37}},"slice20":{"slice20":{"name":"slice20","width":176,"height":145,"x":61.95,"y":-15.87,"rotation":144.46}},"slice4":{"slice4":{"name":"slice4","width":171,"height":159,"x":27.81,"y":-6.11,"rotation":125.55}},"slice17":{"slice17":{"name":"slice17","width":182,"height":92,"x":51.4,"y":3.78,"rotation":-173.5}},"fx3":{"fx3":{"name":"fx3","width":304,"height":247,"x":37.55,"y":-144.35,"rotation":-90,"scaleX":1.5312,"scaleY":1.5312}},"slice12":{"slice12":{"name":"slice12","width":182,"height":91,"x":70.67,"y":-0.32,"rotation":1.94}},"slice6":{"slice6":{"name":"slice6","width":104,"height":96,"x":21.61,"y":-13.91,"rotation":84.83}},"slice15":{"slice15":{"name":"slice15","width":154,"height":113,"x":59.45,"y":-8.26,"rotation":143.2}},"fx1":{"fx1":{"name":"fx1","width":211,"height":179,"x":83.67,"y":-18.16,"rotation":-90}},"slice10":{"slice10":{"name":"slice10","width":124,"height":79,"x":36.65,"y":1.53,"rotation":148.18}},"slice2":{"slice2":{"name":"slice2","width":142,"height":140,"x":34.73,"y":1.43,"rotation":54.75}},"explode1":{"explode1":{"name":"explode1","width":204,"height":147,"x":1.71,"y":10.05,"rotation":-89.21},"explode2":{"name":"explode2","width":207,"height":165,"x":1.71,"y":10.05,"rotation":-89.21},"explode3":{"name":"explode3","width":244,"height":193,"x":1.71,"y":10.05,"rotation":-89.21},"explode4":{"name":"explode4","width":230,"height":190,"x":1.71,"y":10.05,"rotation":-89.21},"explode5":{"name":"explode5","width":229,"height":190,"x":1.71,"y":10.05,"rotation":-89.21},"explode6":{"name":"explode6","width":206,"height":166,"x":1.71,"y":10.05,"rotation":-89.21},"explode7":{"name":"explode7","width":180,"height":169,"x":1.71,"y":10.05,"rotation":-89.21},"explode8":{"name":"explode8","width":176,"height":167,"x":1.71,"y":10.05,"rotation":-89.21},"explode9":{"name":"explode9","width":170,"height":171,"x":1.71,"y":10.05,"rotation":-89.21}},"slice13":{"slice13":{"name":"slice13","width":292,"height":127,"x":96.92,"y":-6.91,"rotation":177.91}},"slice8":{"slice8":{"name":"slice8","width":116,"height":74,"x":33.51,"y":-5.88,"rotation":149.67}},"fx11":{"fx1":{"name":"fx1","width":211,"height":179,"x":86.14,"y":25.46,"rotation":90,"scaleY":-1}},"slice11":{"slice11":{"name":"slice11","width":69,"height":55,"x":20.19,"y":-1.71,"rotation":16.19}},"slice5":{"slice5":{"name":"slice5","width":177,"height":148,"x":42.76,"y":-13.04,"rotation":129.63}},"slice7":{"slice7":{"name":"slice7","width":105,"height":107,"x":25.72,"y":-19.58,"rotation":93.18}}}},"animations":{"idle":{"bones":{"bone":{"translate":[{"time":0},{"time":0.625,"y":-5.46},{"time":1.25}]},"bone1":{"rotate":[{"time":0,"angle":-22.15}],"shear":[{"time":0}]},"bone2":{"rotate":[{"time":0,"angle":-32.83}],"shear":[{"time":0}]},"bone3":{"rotate":[{"time":0,"angle":0},{"time":0.9167,"angle":0},{"time":1.0417,"angle":-17.09},{"time":1.25,"angle":0}],"shear":[{"time":0},{"time":0.9167},{"time":1.0417},{"time":1.25}]},"bone4":{"rotate":[{"time":0,"angle":0},{"time":0.9167,"angle":0},{"time":1.0417,"angle":35.05},{"time":1.25,"angle":0}],"shear":[{"time":0},{"time":0.9167},{"time":1.0417},{"time":1.25}]},"bone5":{"rotate":[{"time":0,"angle":-15.94}],"shear":[{"time":0}]},"bone6":{"rotate":[{"time":0,"angle":15.99}],"shear":[{"time":0}]},"bone10":{"rotate":[{"time":0,"angle":0.25}],"shear":[{"time":0}]},"bone11":{"rotate":[{"time":0,"angle":-0.11}],"shear":[{"time":0}]},"bone15":{"rotate":[{"time":0,"angle":-3.67}],"shear":[{"time":0}]},"bone16":{"rotate":[{"time":0,"angle":-12.92}],"shear":[{"time":0}]},"bone17":{"rotate":[{"time":0,"angle":0},{"time":0.2917,"angle":18.09},{"time":0.4167,"angle":0}],"shear":[{"time":0},{"time":0.2917},{"time":0.4167}]},"bone18":{"rotate":[{"time":0,"angle":0},{"time":0.2917,"angle":-21.18},{"time":0.4167,"angle":0}],"shear":[{"time":0},{"time":0.2917},{"time":0.4167}]}}},"walk":{"bones":{"bone":{"translate":[{"time":0,"x":4.2,"y":-33.9},{"time":0.1667,"x":4.2,"y":-11.34},{"time":0.3334,"x":4.2,"y":-33.9},{"time":0.5001,"x":4.2,"y":-11.34},{"time":0.6668,"x":4.2,"y":-33.9}]},"bone1":{"rotate":[{"time":0,"angle":-22.15}],"shear":[{"time":0}]},"bone2":{"rotate":[{"time":0,"angle":-32.83}],"shear":[{"time":0}]},"bone5":{"rotate":[{"time":0,"angle":-15.94}],"shear":[{"time":0}]},"bone6":{"rotate":[{"time":0,"angle":15.99}],"shear":[{"time":0}]},"bone7":{"translate":[{"time":0},{"time":0.3333,"x":-4.84,"y":-19.31},{"time":0.6666}]},"bone8":{"rotate":[{"time":0,"angle":0},{"time":0.1667,"angle":15.36},{"time":0.3334,"angle":-1.12},{"time":0.6667,"angle":0}],"shear":[{"time":0},{"time":0.1667},{"time":0.3334},{"time":0.6667}]},"bone9":{"rotate":[{"time":0,"angle":0},{"time":0.1667,"angle":-33.27},{"time":0.3334,"angle":-1.79},{"time":0.6667,"angle":0}],"shear":[{"time":0},{"time":0.1667},{"time":0.3334},{"time":0.6667}]},"bone10":{"rotate":[{"time":0,"angle":0.25}],"shear":[{"time":0}]},"bone11":{"rotate":[{"time":0,"angle":-0.11}],"shear":[{"time":0}]},"bone13":{"rotate":[{"time":0,"angle":0},{"time":0.3333,"angle":-7.37},{"time":0.5,"angle":14.73},{"time":0.6667,"angle":0}],"shear":[{"time":0},{"time":0.3333},{"time":0.5},{"time":0.6667}]},"bone14":{"rotate":[{"time":0,"angle":0},{"time":0.3333,"angle":-1.81},{"time":0.5,"angle":-17.29},{"time":0.6667,"angle":0}],"shear":[{"time":0},{"time":0.3333},{"time":0.5},{"time":0.6667}]},"bone15":{"rotate":[{"time":0,"angle":-3.67}],"shear":[{"time":0}]},"bone16":{"rotate":[{"time":0,"angle":-12.92}],"shear":[{"time":0}]},"bone_ikTarget":{"translate":[{"time":0,"x":56.52,"y":-1.1},{"time":0.1667,"x":-9.18,"y":36.06},{"time":0.3334,"x":-74.88,"y":-17.03},{"time":0.6667,"x":56.52,"y":-1.1}]},"bone_ikTarget1":{"translate":[{"time":0,"x":-73.83,"y":-0.5},{"time":0.3333,"x":133.02,"y":1.09},{"time":0.5,"x":29.59,"y":32.15},{"time":0.6667,"x":-73.83,"y":-0.5}]},"bone_ikTarget4":{"translate":[{"time":0},{"time":0.3333,"x":-6.64},{"time":0.6666}]},"bone_ikTarget5":{"translate":[{"time":0,"curve":"stepped"},{"time":0.3333,"x":-6.37,"y":-0.86}]}}},"attack1":{"bones":{"bone":{"translate":[{"time":0},{"time":0.1667,"y":-37.13},{"time":0.25,"curve":"stepped","x":-106.86,"y":-37.13},{"time":0.2917,"x":-140.38,"y":-73.04},{"time":0.375,"x":-140.38,"y":-89.8},{"time":0.4583,"x":-104.38,"y":-67.65}],"rotate":[{"time":0,"angle":0},{"time":0.25,"curve":"stepped","angle":0},{"time":0.2917,"angle":12.94}],"shear":[{"time":0},{"time":0.25,"curve":"stepped"},{"time":0.2917}]},"bone1":{"rotate":[{"time":0,"angle":-22.15},{"time":0.1667,"angle":-16.83},{"time":0.25,"angle":-2.26}],"shear":[{"time":0},{"time":0.1667},{"time":0.25}]},"bone2":{"rotate":[{"time":0,"angle":-32.83},{"time":0.1667,"angle":-63.47},{"time":0.25,"angle":-49.61}],"shear":[{"time":0},{"time":0.1667},{"time":0.25}]},"bone5":{"rotate":[{"time":0,"angle":-15.94},{"time":0.1667,"angle":-5.97},{"time":0.25,"angle":19.57}],"shear":[{"time":0},{"time":0.1667},{"time":0.25}]},"bone6":{"rotate":[{"time":0,"angle":15.99},{"time":0.1667,"angle":-14.82},{"time":0.25,"angle":19.41}],"shear":[{"time":0},{"time":0.1667},{"time":0.25}]},"bone7":{"translate":[{"time":0},{"time":0.1667,"x":-5.3,"y":-11.2}],"rotate":[{"time":0,"angle":0},{"time":0.1667,"angle":21.87},{"time":0.25,"angle":-34.91}],"shear":[{"time":0},{"time":0.1667},{"time":0.25}]},"bone10":{"rotate":[{"time":0,"angle":0.25},{"time":0.1667,"angle":-51.04},{"time":0.25,"angle":4.6}],"shear":[{"time":0},{"time":0.1667},{"time":0.25}]},"bone11":{"rotate":[{"time":0,"angle":-0.11},{"time":0.1667,"angle":30.41},{"time":0.25,"angle":-15.36}],"shear":[{"time":0},{"time":0.1667},{"time":0.25}]},"bone12":{"translate":[{"time":0},{"time":0.0833,"x":-1.49,"y":-10.29}],"rotate":[{"time":0,"angle":0},{"time":0.1667,"angle":22.31},{"time":0.25,"angle":13.92}],"shear":[{"time":0},{"time":0.1667},{"time":0.25}]},"bone15":{"rotate":[{"time":0,"angle":-3.67},{"time":0.1667,"angle":12.74},{"time":0.25,"angle":164.12}],"shear":[{"time":0},{"time":0.1667},{"time":0.25}]},"bone16":{"rotate":[{"time":0,"angle":-12.92},{"time":0.1667,"angle":-40.04},{"time":0.25,"angle":9.93}],"shear":[{"time":0},{"time":0.1667},{"time":0.25}]},"bone17":{"rotate":[{"time":0,"angle":11.28},{"time":0.1667,"curve":"stepped","angle":-10.64},{"time":0.2084,"curve":"stepped","angle":-3.45},{"time":0.2501,"angle":19.91}],"shear":[{"time":0},{"time":0.1667,"curve":"stepped"},{"time":0.2084,"curve":"stepped"},{"time":0.2501}]},"bone18":{"rotate":[{"time":0,"angle":-16.38},{"time":0.1667,"angle":21.17},{"time":0.2084,"angle":10.16},{"time":0.2501,"angle":-22.79}],"shear":[{"time":0},{"time":0.1667},{"time":0.2084},{"time":0.2501}]},"bone_ikTarget":{"translate":[{"time":0},{"time":0.1667,"x":-1.33,"y":-8.28}]},"bone_ikTarget1":{"translate":[{"time":0},{"time":0.0833,"x":-53.14,"y":29.82},{"time":0.1666,"x":-106.27,"y":-9.37}]},"bone_ikTarget2":{"translate":[{"time":0},{"time":0.1667,"curve":"stepped","x":72.88,"y":241.87},{"time":0.25,"curve":"stepped","x":72.88,"y":241.87},{"time":0.2917,"x":-269.86,"y":-158.45},{"time":0.4584,"x":-182.36,"y":-135.19}],"rotate":[{"time":0,"angle":0},{"time":0.25,"curve":"stepped","angle":0},{"time":0.2917,"angle":5.93}],"shear":[{"time":0},{"time":0.25,"curve":"stepped"},{"time":0.2917}]},"bone_ikTarget3":{"translate":[{"time":0},{"time":0.1667},{"time":0.25,"curve":"stepped","x":-76.47,"y":-38.14},{"time":0.375,"x":-98.82,"y":-74.56}]},"bone19":{"translate":[{"time":0},{"time":0.1667},{"time":0.25,"x":-13.67,"y":-31.44}],"rotate":[{"time":0,"angle":0},{"time":0.1667,"angle":0},{"time":0.25,"angle":-3.6}],"shear":[{"time":0},{"time":0.1667},{"time":0.25}]},"bone20":{"translate":[{"time":0},{"time":0.1667},{"time":0.25,"x":-12.3,"y":28.71}]},"bone21":{"rotate":[{"time":0,"angle":0},{"time":0.1667,"curve":"stepped","angle":0},{"time":0.25,"angle":-3.02}],"shear":[{"time":0},{"time":0.1667,"curve":"stepped"},{"time":0.25}]},"bone22":{"translate":[{"time":0},{"time":0.25,"curve":"stepped"},{"time":0.2917,"x":38.57,"y":-9.23}],"rotate":[{"time":0,"angle":0},{"time":0.25,"curve":"stepped","angle":0},{"time":0.2917,"angle":-0.41}],"shear":[{"time":0},{"time":0.25,"curve":"stepped"},{"time":0.2917}]}},"slots":{"slice35":{"attachment":[{"time":0,"name":""},{"time":0.2917,"name":"slice35"}],"color":[{"time":0,"curve":"stepped","color":"FFFFFFFF"},{"time":0.375,"color":"FFFFFFFF"},{"time":0.4583,"color":"FFFFFF1F"}]}},"drawOrder":[{"time":0},{"time":0.2917,"offsets":[{"slot":"fx3","offset":-17}]}]},"attack2":{"bones":{"bone":{"translate":[{"time":0},{"time":0.1667,"y":-37.13},{"time":0.25,"x":-106.86,"y":-37.13},{"time":0.375,"x":-106.86,"y":-43.91}]},"bone1":{"rotate":[{"time":0,"angle":-22.15},{"time":0.1667,"angle":-16.83}],"shear":[{"time":0},{"time":0.1667}]},"bone2":{"rotate":[{"time":0,"angle":-32.83},{"time":0.1667,"angle":-63.47}],"shear":[{"time":0},{"time":0.1667}]},"bone5":{"rotate":[{"time":0,"angle":-15.94},{"time":0.1667,"angle":-5.97}],"shear":[{"time":0},{"time":0.1667}]},"bone6":{"rotate":[{"time":0,"angle":15.99},{"time":0.1667,"angle":-14.82}],"shear":[{"time":0},{"time":0.1667}]},"bone7":{"translate":[{"time":0},{"time":0.1667,"x":-5.3,"y":-11.2}],"rotate":[{"time":0,"angle":0},{"time":0.1667,"angle":21.87}],"shear":[{"time":0},{"time":0.1667}]},"bone10":{"rotate":[{"time":0,"angle":0.25},{"time":0.1667,"angle":-51.04}],"shear":[{"time":0},{"time":0.1667}]},"bone11":{"rotate":[{"time":0,"angle":-0.11},{"time":0.1667,"angle":30.41}],"shear":[{"time":0},{"time":0.1667}]},"bone12":{"translate":[{"time":0},{"time":0.0833,"x":-1.49,"y":-10.29}],"rotate":[{"time":0,"angle":0},{"time":0.1667,"angle":22.31}],"shear":[{"time":0},{"time":0.1667}]},"bone15":{"rotate":[{"time":0,"angle":-3.67},{"time":0.1667,"angle":12.74}],"shear":[{"time":0},{"time":0.1667}]},"bone16":{"rotate":[{"time":0,"angle":-12.92},{"time":0.1667,"angle":-40.04}],"shear":[{"time":0},{"time":0.1667}]},"bone17":{"rotate":[{"time":0,"angle":11.28},{"time":0.1667,"curve":"stepped","angle":-10.64},{"time":0.2084,"curve":"stepped","angle":-3.45},{"time":0.2501,"angle":19.91}],"shear":[{"time":0},{"time":0.1667,"curve":"stepped"},{"time":0.2084,"curve":"stepped"},{"time":0.2501}]},"bone18":{"rotate":[{"time":0,"angle":-16.38},{"time":0.1667,"angle":21.17},{"time":0.2084,"angle":10.16},{"time":0.2501,"angle":-22.79}],"shear":[{"time":0},{"time":0.1667},{"time":0.2084},{"time":0.2501}]},"bone_ikTarget":{"translate":[{"time":0},{"time":0.1667,"x":-1.33,"y":-8.28}]},"bone_ikTarget1":{"translate":[{"time":0},{"time":0.0833,"x":-53.14,"y":29.82},{"time":0.1666,"x":-106.27,"y":-9.37}]},"bone_ikTarget2":{"translate":[{"time":0},{"time":0.1667,"curve":"stepped","x":15.78,"y":17.29},{"time":0.2084,"curve":"stepped","x":-29.33,"y":10.45},{"time":0.2501,"x":-261.46,"y":-4.15},{"time":0.3751,"x":-271.03,"y":-4.15}]},"bone19":{"translate":[{"time":0},{"time":0.1667},{"time":0.25,"x":-13.67,"y":-31.44}],"rotate":[{"time":0,"angle":0},{"time":0.1667,"angle":0},{"time":0.25,"angle":-3.6}],"shear":[{"time":0},{"time":0.1667},{"time":0.25}]},"bone20":{"translate":[{"time":0},{"time":0.1667},{"time":0.25,"x":-12.3,"y":28.71}]},"bone21":{"rotate":[{"time":0,"angle":0},{"time":0.1667,"curve":"stepped","angle":0},{"time":0.25,"angle":-3.02}],"shear":[{"time":0},{"time":0.1667,"curve":"stepped"},{"time":0.25}]}},"slots":{"fx1":{"attachment":[{"time":0,"name":""},{"time":0.25,"name":"fx1"},{"time":0.375,"name":""}],"color":[{"time":0,"curve":"stepped","color":"FFFFFFFF"},{"time":0.2917,"color":"FFFFFF36"}]},"fx11":{"attachment":[{"time":0,"name":""},{"time":0.25,"name":"fx1"},{"time":0.375,"name":""}],"color":[{"time":0,"curve":"stepped","color":"FFFFFFFF"},{"time":0.2917,"color":"FFFFFF54"}]},"fx4":{"attachment":[{"time":0,"name":""},{"time":0.25,"name":"fx4"},{"time":0.2917,"name":""}]}}},"get_hit":{"bones":{"bone":{"translate":[{"time":0,"x":15.96,"y":-24.83},{"time":0.0833,"x":44.33,"y":-32.51},{"time":0.25}],"rotate":[{"time":0,"angle":16.51},{"time":0.25,"angle":0}],"shear":[{"time":0},{"time":0.25}]},"bone1":{"rotate":[{"time":0,"angle":-22.15}],"shear":[{"time":0}]},"bone2":{"rotate":[{"time":0,"angle":-32.83}],"shear":[{"time":0}]},"bone5":{"rotate":[{"time":0,"angle":-15.94}],"shear":[{"time":0}]},"bone6":{"rotate":[{"time":0,"angle":15.99}],"shear":[{"time":0}]},"bone10":{"rotate":[{"time":0,"angle":0.25}],"shear":[{"time":0}]},"bone11":{"rotate":[{"time":0,"angle":-0.11}],"shear":[{"time":0}]},"bone15":{"rotate":[{"time":0,"angle":-3.67}],"shear":[{"time":0}]},"bone16":{"rotate":[{"time":0,"angle":-12.92}],"shear":[{"time":0}]},"bone_ikTarget2":{"translate":[{"time":0,"x":-5.32,"y":-76.25},{"time":0.25}]},"bone_ikTarget3":{"translate":[{"time":0,"x":-61.09,"y":-56.92},{"time":0.25}]}},"slots":{"slice1":{"color":[{"time":0,"color":"BA0303FF"},{"time":0.1667,"color":"FFFFFFFF"}]}}},"dead":{"bones":{"bone":{"translate":[{"time":0,"x":15.96,"y":-24.83},{"time":0.0833,"x":44.33,"y":-32.51},{"time":0.3333,"curve":"stepped","x":44.33,"y":-32.51},{"time":0.375,"x":89.69,"y":-179.85},{"time":0.625,"x":95.16,"y":-178.85},{"time":0.75,"x":97.9,"y":-194.62}],"rotate":[{"time":0,"angle":16.51},{"time":0.1667,"angle":-4.17},{"time":0.3334,"curve":"stepped","angle":14.39},{"time":0.3751,"angle":-13.82}],"shear":[{"time":0},{"time":0.1667},{"time":0.3334,"curve":"stepped"},{"time":0.3751}]},"bone1":{"rotate":[{"time":0,"angle":-22.15},{"time":0.3333,"angle":-66.08}],"shear":[{"time":0},{"time":0.3333}]},"bone2":{"rotate":[{"time":0,"angle":-32.83},{"time":0.3333,"angle":-11.36}],"shear":[{"time":0},{"time":0.3333}]},"bone3":{"rotate":[{"time":0,"angle":-26.43}],"shear":[{"time":0}]},"bone4":{"rotate":[{"time":0,"angle":24.05}],"shear":[{"time":0}]},"bone5":{"rotate":[{"time":0,"angle":-15.94},{"time":0.3333,"angle":-32.43}],"shear":[{"time":0},{"time":0.3333}]},"bone6":{"rotate":[{"time":0,"angle":15.99},{"time":0.3333,"angle":3.73}],"shear":[{"time":0},{"time":0.3333}]},"bone7":{"rotate":[{"time":0,"angle":0},{"time":0.3333,"angle":14.75}],"shear":[{"time":0},{"time":0.3333}]},"bone10":{"rotate":[{"time":0,"angle":0.25},{"time":0.3333,"angle":-40.5}],"shear":[{"time":0},{"time":0.3333}]},"bone11":{"rotate":[{"time":0,"angle":-0.11},{"time":0.3333,"angle":-12.15}],"shear":[{"time":0},{"time":0.3333}]},"bone12":{"rotate":[{"time":0,"angle":0},{"time":0.3333,"angle":36.14}],"shear":[{"time":0},{"time":0.3333}]},"bone15":{"rotate":[{"time":0,"angle":-3.67},{"time":0.3333,"angle":-30.74}],"shear":[{"time":0},{"time":0.3333}]},"bone16":{"rotate":[{"time":0,"angle":-12.92},{"time":0.3333,"angle":-0.5}],"shear":[{"time":0},{"time":0.3333}]},"bone17":{"rotate":[{"time":0,"angle":31.31},{"time":0.3333,"curve":"stepped","angle":31.31},{"time":0.4166,"angle":-11.12}],"shear":[{"time":0},{"time":0.3333,"curve":"stepped"},{"time":0.4166}]},"bone18":{"rotate":[{"time":0,"angle":0},{"time":0.3333,"curve":"stepped","angle":0},{"time":0.4166,"angle":-53.89}],"shear":[{"time":0},{"time":0.3333,"curve":"stepped"},{"time":0.4166}]},"bone_ikTarget":{"translate":[{"time":0},{"time":0.0833,"x":-39.46},{"time":0.1666,"x":-39.46,"y":4.57},{"time":0.2499,"x":-39.46,"y":34.38},{"time":0.3332,"curve":"stepped","x":23.62,"y":4.42},{"time":0.3749,"x":139.98,"y":-6.25}]},"bone_ikTarget1":{"translate":[{"time":0},{"time":0.0833,"x":102.61,"y":35.64},{"time":0.1666,"x":102.61,"y":-3.82},{"time":0.2499,"x":-16.06,"y":-3.82},{"time":0.3332,"curve":"stepped","x":-16.06,"y":-3.82},{"time":0.3749,"x":162.84,"y":1.1}]},"bone_ikTarget2":{"translate":[{"time":0,"x":-5.32,"y":-76.25},{"time":0.3333,"curve":"stepped","x":-5.32,"y":-76.25},{"time":0.4166,"x":17.66,"y":-219.04},{"time":0.4999,"x":7.81,"y":-168.16},{"time":0.5832,"x":71.82,"y":-214.12}]},"bone_ikTarget3":{"translate":[{"time":0,"x":-61.09,"y":-56.92},{"time":0.3333,"curve":"stepped","x":-61.09,"y":-56.92},{"time":0.4166,"x":-64.37,"y":-257.16},{"time":0.4999,"x":-76.68,"y":-218.92},{"time":0.5832,"x":-48.29,"y":-260.61}]},"bone23":{"translate":[{"time":0},{"time":0.3333,"curve":"stepped"},{"time":0.75,"x":-535.09,"y":-14.23},{"time":0.8333,"x":-535.09,"y":21.67}]}},"slots":{"slice1":{"attachment":[{"time":0,"name":"slice1"},{"time":1,"name":""}],"color":[{"time":0,"color":"BA0303FF"},{"time":0.0833,"color":"FFFFFFFF"}]},"explode1":{"attachment":[{"time":0,"name":""},{"time":0.75,"name":"explode1"},{"time":0.8333,"name":"explode2"},{"time":0.9166,"name":"explode3"},{"time":0.9999,"name":"explode4"},{"time":1.0832,"name":"explode5"},{"time":1.1665,"name":"explode6"},{"time":1.2498,"name":"explode7"},{"time":1.3331,"name":"explode8"},{"time":1.4164,"name":"explode9"},{"time":1.4997,"name":""}]}},"drawOrder":[{"time":0},{"time":0.75,"offsets":[{"slot":"explode1","offset":-8}]}]}}}